pypi_timemachine/__init__.py
pypi_timemachine/__main__.py
pypi_timemachine/core.py
pypi_timemachine/tests/__init__.py
pypi_timemachine/tests/test_basic.py
pypi_timemachine-0.3.1.dist-info/licenses/LICENSE
pypi_timemachine-0.3.1.dist-info/METADATA
pypi_timemachine-0.3.1.dist-info/WHEEL
pypi_timemachine-0.3.1.dist-info/entry_points.txt
pypi_timemachine-0.3.1.dist-info/top_level.txt
pypi_timemachine-0.3.1.dist-info/RECORD
